makemigrations.py
manage.py
runtests.py
account/__init__.py
account/admin.py
account/auth_backends.py
account/conf.py
account/context_processors.py
account/decorators.py
account/fields.py
account/forms.py
account/hooks.py
account/languages.py
account/managers.py
account/middleware.py
account/mixins.py
account/models.py
account/signals.py
account/timezones.py
account/urls.py
account/utils.py
account/views.py
account/locale/ar/LC_MESSAGES/django.mo
account/locale/ar/LC_MESSAGES/django.po
account/locale/de/LC_MESSAGES/django.mo
account/locale/de/LC_MESSAGES/django.po
account/locale/es/LC_MESSAGES/django.mo
account/locale/es/LC_MESSAGES/django.po
account/locale/fa_IR/LC_MESSAGES/django.mo
account/locale/fa_IR/LC_MESSAGES/django.po
account/locale/fr/LC_MESSAGES/django.mo
account/locale/fr/LC_MESSAGES/django.po
account/locale/it/LC_MESSAGES/django.mo
account/locale/it/LC_MESSAGES/django.po
account/locale/ja/LC_MESSAGES/django.mo
account/locale/ja/LC_MESSAGES/django.po
account/locale/nl/LC_MESSAGES/django.mo
account/locale/nl/LC_MESSAGES/django.po
account/locale/pl/LC_MESSAGES/django.mo
account/locale/pl/LC_MESSAGES/django.po
account/locale/pt_BR/LC_MESSAGES/django.mo
account/locale/pt_BR/LC_MESSAGES/django.po
account/locale/ru/LC_MESSAGES/django.mo
account/locale/ru/LC_MESSAGES/django.po
account/locale/sk_SK/LC_MESSAGES/django.mo
account/locale/sk_SK/LC_MESSAGES/django.po
account/locale/tr/LC_MESSAGES/django.mo
account/locale/tr/LC_MESSAGES/django.po
account/locale/zh_CN/LC_MESSAGES/django.mo
account/locale/zh_CN/LC_MESSAGES/django.po
account/locale/zh_TW/LC_MESSAGES/django.mo
account/locale/zh_TW/LC_MESSAGES/django.po
account/management/__init__.py
account/management/commands/__init__.py
account/management/commands/expunge_deleted.py
account/management/commands/user_password_expiry.py
account/management/commands/user_password_history.py
account/migrations/0001_initial.py
account/migrations/0002_fix_str.py
account/migrations/0003_passwordexpiry_passwordhistory.py
django_user_accounts-3.3.2.dist-info/LICENSE
django_user_accounts-3.3.2.dist-info/METADATA
django_user_accounts-3.3.2.dist-info/WHEEL
django_user_accounts-3.3.2.dist-info/top_level.txt
django_user_accounts-3.3.2.dist-info/RECORD
