Metadata-Version: 2.1
Name: django-user-accounts
Version: 3.3.2
Summary: a Django user account app
Author-email: Pinax Team <team@pinaxproject.com>
Project-URL: Homepage, http://github.com/pinax/django-user-accounts
Classifier: Development Status :: 5 - Production/Stable
Classifier: Environment :: Web Environment
Classifier: Framework :: Django
Classifier: Framework :: Django :: 3.2
Classifier: Framework :: Django :: 4.2
Classifier: Intended Audience :: Developers
Classifier: License :: OSI Approved :: MIT License
Classifier: Operating System :: OS Independent
Classifier: Programming Language :: Python
Classifier: Programming Language :: Python :: 3
Classifier: Programming Language :: Python :: 3.8
Classifier: Programming Language :: Python :: 3.9
Classifier: Programming Language :: Python :: 3.10
Classifier: Programming Language :: Python :: 3.11
License-File: LICENSE
Requires-Dist: Django>=3.2
Requires-Dist: django-appconf>=1.0.4
Requires-Dist: pytz>=2020.4
